ez_eda/.ipynb_checkpoints/__init__-checkpoint.py
ez_eda/.ipynb_checkpoints/main-checkpoint.py
ez_eda/__init__.py
ez_eda/main.py
ez_eda-0.1.3.dist-info/WHEEL
ez_eda-0.1.3.dist-info/METADATA
ez_eda-0.1.3.dist-info/LICENSE
ez_eda-0.1.3.dist-info/RECORD
