Metadata-Version: 2.1
Name: ez-eda
Version: 0.1.3
Summary: simple EDA (Exploratory Data Analysis) visuals
Home-page: https://github.com/van-william/ez-eda
License: MIT
Author: William VanBuskirk
Author-email: william.n.vanbuskirk@gmail.com
Requires-Python: >=3.9,<4.0
Classifier: License :: OSI Approved :: MIT License
Classifier: Programming Language :: Python :: 3
Classifier: Programming Language :: Python :: 3.9
Classifier: Programming Language :: Python :: 3.10
Classifier: Programming Language :: Python :: 3.11
Requires-Dist: pandas (>=1.5.2,<2.0.0)
Requires-Dist: seaborn (>=0.12.1,<0.13.0)
Project-URL: Repository, https://github.com/van-william/ez-eda
